{"intents": [
    {"tag": "greeting",
     "patterns": ["Hi", "Hey", "Is anyone there?", "Hello", "Yo!"],
     "responses": ["Hello", "Hi", "Hi there", "Wosop", "Hellooo", "What's UP?"]
    },
    {"tag": "goodbye",
     "patterns": ["Bye", "See you later", "Goodbye"],
     "responses": ["See you later", "Have a nice day", "Bye! Come back again"]
    },
    {"tag": "thanks",
     "patterns": ["Thanks", "Thank you", "That's helpful", "Thanks for the help"],
     "responses": ["Happy to help!", "Any time!", "My pleasure", "You're most welcome!"]
    },
    {"tag": "about",
     "patterns": ["Who are you?", "What are you?","Tell me about Yourself." ],
     "responses": ["I'm BRESLIN, your Bot assistant", "I'm BRESLIN, an Artificial Intelligent Bot" , "Your Personal A.I Bot"]
    },
    {"tag": "name",
    "patterns": ["what is your name", "what should I call you", "whats your name?"],
    "responses": ["You can call me BRESLIN.", "I'm AGENT BRESLIN!", "Just call me as BRESLIN"]
    },
    {"tag": "help",
    "patterns": ["Can you help me?", "give me a hand please", "Can you help?", "What can you do for me?", "I need assistance", "I need help", "I need some Insight"],
    "responses": ["Tell me how can assist you", "Tell me your problem to assist you", "Yes Sure, How can I help you"]
    },
    {"tag": "createaccount",
    "patterns": ["I need to create a new account", "how to open a new account", "I want to create an account", "can you create an account for me", "how to open a new account"],
    "responses": ["You can just easily create a new account from our web site", "Just go to our web site and follow the guidelines to create a new account"]
    },
    {"tag": "complaint",
    "patterns": ["I have a Problem", "I want to raise a complaint", "There is a complaint about a service"],
    "responses": ["Please provide us your complaint in order to assist you", "Please mention your complaint", "We will reach you... And sorry for any Inconvenience caused"]
    },
    {"tag": "contact",
    "patterns": ["How can i reach you?", "What are your contact details", "Can i get your contact details?", "Email?"],
    "responses": ["Our Email is : cypherrix5@gmail.com", "Reach Us on : cypherrix5@gmail.com"]
    }
]
}